heavytailed/__init__.py
heavytailed/base_distribution.py
heavytailed/compare.py
heavytailed/exponential.py
heavytailed/lognormal.py
heavytailed/pairwise_powerlaw.py
heavytailed/poisson.py
heavytailed/powerlaw.py
heavytailed/powerlaw_exp.py
heavytailed/shifted_powerlaw_exp.py
heavytailed/trunc_lognormal.py
heavytailed/trunc_powerlaw.py
heavytailed/yule.py
heavytailed-1.0.3.dist-info/LICENSE
heavytailed-1.0.3.dist-info/METADATA
heavytailed-1.0.3.dist-info/WHEEL
heavytailed-1.0.3.dist-info/top_level.txt
heavytailed-1.0.3.dist-info/zip-safe
heavytailed-1.0.3.dist-info/RECORD
