Metadata-Version: 2.1
Name: heavytailed
Version: 1.0.3
Summary: Perform distribution analysis on heavy-tailed distributed data
Home-page: https://github.com/XiangwenWang/heavytailed
Author: Xiangwen Wang
Author-email: wangxiangwen1989@gmail.com
License: BSD 2-Clause License
Keywords: heavy-tailed,distribution analysis
Platform: any
Classifier: Development Status :: 5 - Production/Stable
Classifier: Intended Audience :: Developers
Classifier: License :: OSI Approved :: BSD License
Classifier: Operating System :: OS Independent
Classifier: Programming Language :: Python :: 2
Classifier: Programming Language :: Python :: 2.7
Classifier: Programming Language :: Python :: 3
Classifier: Programming Language :: Python :: 3.4
Classifier: Programming Language :: Python :: 3.5
Classifier: Programming Language :: Python :: 3.6
Classifier: Programming Language :: Python :: 3.7
Classifier: Programming Language :: Python :: 3.8
Requires-Dist: numpy
Requires-Dist: scipy
Requires-Dist: pandas
Requires-Dist: mpmath
Requires-Dist: matplotlib
